README.md
setup.py
linear_regression_model/__init__.py
linear_regression_model/functions.py
linear_regression_model.egg-info/PKG-INFO
linear_regression_model.egg-info/SOURCES.txt
linear_regression_model.egg-info/dependency_links.txt
linear_regression_model.egg-info/requires.txt
linear_regression_model.egg-info/top_level.txt