Metadata-Version: 2.1
Name: linear-regression-model
Version: 0.1
